[
  {
    "Name": "BasicAttack_GreatSword",
    "SkillData": {
      "SkillNameTag": "Arcanum.Skills.BasicAttack.GreatSword",
      "DisplayName": "대검 기본 공격",
      "SkillTypeTag": "Arcanum.Skills.SkillTypes.Active",
      "TargetTypeTag": "Arcanum.Skills.TargetingType.Unit",
      "TargetFilterTag": "Arcanum.Skills.TargetFilter.Enemy",
      "SkillVFXTag": [ "Arcanum.Skills.SkillVFX.None" ],
      "Icon": "",
      "CurrLevel": 0,
      "LevelModifiers": [
        {
          "Level": 0,
          "CastTime": 0.4,
          "Cooldown": 0.0,
          "Cost": [],
          "Effect": "",
          "OtherCharacterModifiers": [
            {
              "ModifierId": {
                "A": 0,
                "B": 0,
                "C": 0,
                "D": 0
              },
              "SourceTag": "Arcanum.Skills.BasicAttack.GreatSword",
              "StatTag": "Arcanum.BattleStat.Character.Regen.Health.Value",
              "ApplyTargetFilterTag": "Arcanum.Skills.TargetFilter.Enemy",
              "Value": {
                "Flat": -10.0,
                "Mul": 0.0
              },
              "bIsPermanent": false,
              "bAllowRefresh": true,
              "Duration": 0.0,
              "ModifierPolicy": "Refresh",
              "MaxStack": 1
            }
          ],
          "TargetEffect": ""
        },
        {
          "Level": 1,
          "CastTime": 0.4,
          "OtherCharacterModifiers": [
            {
              "ModifierId": {
                "A": 0,
                "B": 0,
                "C": 0,
                "D": 0
              },
              "SourceTag": "Arcanum.Skills.BasicAttack.GreatSword",
              "StatTag": "Arcanum.BattleStat.Character.Regen.Health.Value",
              "Value": {
                "Flat": -14.0,
                "Mul": 0.0
              },
              "bIsPermanent": false,
              "bAllowRefresh": true,
              "Duration": 0.0,
              "ModifierPolicy": "Refresh",
              "MaxStack": 1
            }
          ]
        },
        {
          "Level": 2,
          "CastTime": 0.4,
          "OtherCharacterModifiers": [
            {
              "ModifierId": {
                "A": 0,
                "B": 0,
                "C": 0,
                "D": 0
              },
              "SourceTag": "Arcanum.Skills.BasicAttack.GreatSword",
              "StatTag": "Arcanum.BattleStat.Character.Regen.Health.Value",
              "Value": {
                "Flat": -19.0,
                "Mul": 0.0
              },
              "bIsPermanent": false,
              "bAllowRefresh": true,
              "Duration": 0.0,
              "ModifierPolicy": "Refresh",
              "MaxStack": 1
            }
          ]
        },
        {
          "Level": 3,
          "CastTime": 0.4,
          "OtherCharacterModifiers": [
            {
              "ModifierId": {
                "A": 0,
                "B": 0,
                "C": 0,
                "D": 0
              },
              "SourceTag": "Arcanum.Skills.BasicAttack.GreatSword",
              "StatTag": "Arcanum.BattleStat.Character.Regen.Health.Value",
              "Value": {
                "Flat": -25.0,
                "Mul": 0.0
              },
              "bIsPermanent": false,
              "bAllowRefresh": true,
              "Duration": 0.0,
              "ModifierPolicy": "Refresh",
              "MaxStack": 1
            }
          ]
        },
        {
          "Level": 4,
          "CastTime": 0.4,
          "OtherCharacterModifiers": [
            {
              "ModifierId": {
                "A": 0,
                "B": 0,
                "C": 0,
                "D": 0
              },
              "SourceTag": "Arcanum.Skills.BasicAttack.GreatSword",
              "StatTag": "Arcanum.BattleStat.Character.Regen.Health.Value",
              "Value": {
                "Flat": -32.0,
                "Mul": 0.0
              },
              "bIsPermanent": false,
              "bAllowRefresh": true,
              "Duration": 0.0,
              "ModifierPolicy": "Refresh",
              "MaxStack": 1
            }
          ]
        },
        {
          "Level": 5,
          "CastTime": 0.4,
          "OtherCharacterModifiers": [
            {
              "ModifierId": {
                "A": 0,
                "B": 0,
                "C": 0,
                "D": 0
              },
              "SourceTag": "Arcanum.Skills.BasicAttack.GreatSword",
              "StatTag": "Arcanum.BattleStat.Character.Regen.Health.Value",
              "Value": {
                "Flat": -40.0,
                "Mul": 0.0
              },
              "bIsPermanent": false,
              "bAllowRefresh": true,
              "Duration": 0.0,
              "ModifierPolicy": "Refresh",
              "MaxStack": 1
            }
          ]
        }
      ],
      "Targeting": {
        "IndicatorDecal": "",
        "MaxRange": 180.0,
        "Radius": 0.0,
        "Width": 0.0
      },
      "Control": {
        "KnockbackStrength": 0.0,
        "PullStrength": 0.0
      },
      "Awaken": {
        "MaxGauge": 100.0,
        "GainOnBasicHit": 1.0,
        "GainOnWeaponSkillHit": 5.0,
        "DurationSec": 15.0,
        "AuraRadius": 0.0
      },
      "Trigger": { "TriggerSkillTag": "Arcanum.Skills.SkillName.None" }
    },
    "SkillClass": ""
  },
  {
    "Name": "BasicAttack_Staff",
    "SkillData": {
      "SkillNameTag": "Arcanum.Skills.BasicAttack.Staff",
      "DisplayName": "지팡이 기본 공격",
      "SkillTypeTag": "Arcanum.Skills.SkillTypes.Active",
      "TargetTypeTag": "Arcanum.Skills.TargetingType.Unit",
      "TargetFilterTag": "Arcanum.Skills.TargetFilter.Enemy",
      "SkillVFXTag": [ "Arcanum.Skills.SkillVFX.None" ],
      "Icon": "",
      "CurrLevel": 0,
      "LevelModifiers": [
        {
          "Level": 0,
          "CastTime": 0.4,
          "OtherCharacterModifiers": [
            {
              "ModifierId": {
                "A": 0,
                "B": 0,
                "C": 0,
                "D": 0
              },
              "SourceTag": "Arcanum.Skills.BasicAttack.Staff",
              "StatTag": "Arcanum.BattleStat.Character.Regen.Health.Value",
              "ApplyTargetFilterTag": "Arcanum.Skills.TargetFilter.Enemy",
              "Value": {
                "Flat": -10.0,
                "Mul": 0.0
              },
              "bIsPermanent": false,
              "bAllowRefresh": true,
              "Duration": 0.0,
              "ModifierPolicy": "Refresh",
              "MaxStack": 1
            }
          ]
        },
        {
          "Level": 1,
          "CastTime": 0.4,
          "OtherCharacterModifiers": [
            {
              "ModifierId": {
                "A": 0,
                "B": 0,
                "C": 0,
                "D": 0
              },
              "SourceTag": "Arcanum.Skills.BasicAttack.Staff",
              "StatTag": "Arcanum.BattleStat.Character.Regen.Health.Value",
              "Value": {
                "Flat": -14.0,
                "Mul": 0.0
              },
              "bIsPermanent": false,
              "bAllowRefresh": true,
              "Duration": 0.0,
              "ModifierPolicy": "Refresh",
              "MaxStack": 1
            }
          ]
        },
        {
          "Level": 2,
          "CastTime": 0.4,
          "OtherCharacterModifiers": [
            {
              "ModifierId": {
                "A": 0,
                "B": 0,
                "C": 0,
                "D": 0
              },
              "SourceTag": "Arcanum.Skills.BasicAttack.Staff",
              "StatTag": "Arcanum.BattleStat.Character.Regen.Health.Value",
              "Value": {
                "Flat": -19.0,
                "Mul": 0.0
              },
              "bIsPermanent": false,
              "bAllowRefresh": true,
              "Duration": 0.0,
              "ModifierPolicy": "Refresh",
              "MaxStack": 1
            }
          ]
        },
        {
          "Level": 3,
          "CastTime": 0.4,
          "OtherCharacterModifiers": [
            {
              "ModifierId": {
                "A": 0,
                "B": 0,
                "C": 0,
                "D": 0
              },
              "SourceTag": "Arcanum.Skills.BasicAttack.Staff",
              "StatTag": "Arcanum.BattleStat.Character.Regen.Health.Value",
              "Value": {
                "Flat": -25.0,
                "Mul": 0.0
              },
              "bIsPermanent": false,
              "bAllowRefresh": true,
              "Duration": 0.0,
              "ModifierPolicy": "Refresh",
              "MaxStack": 1
            }
          ]
        },
        {
          "Level": 4,
          "CastTime": 0.4,
          "OtherCharacterModifiers": [
            {
              "ModifierId": {
                "A": 0,
                "B": 0,
                "C": 0,
                "D": 0
              },
              "SourceTag": "Arcanum.Skills.BasicAttack.Staff",
              "StatTag": "Arcanum.BattleStat.Character.Regen.Health.Value",
              "Value": {
                "Flat": -32.0,
                "Mul": 0.0
              },
              "bIsPermanent": false,
              "bAllowRefresh": true,
              "Duration": 0.0,
              "ModifierPolicy": "Refresh",
              "MaxStack": 1
            }
          ]
        },
        {
          "Level": 5,
          "CastTime": 0.4,
          "OtherCharacterModifiers": [
            {
              "ModifierId": {
                "A": 0,
                "B": 0,
                "C": 0,
                "D": 0
              },
              "SourceTag": "Arcanum.Skills.BasicAttack.Staff",
              "StatTag": "Arcanum.BattleStat.Character.Regen.Health.Value",
              "Value": {
                "Flat": -40.0,
                "Mul": 0.0
              },
              "bIsPermanent": false,
              "bAllowRefresh": true,
              "Duration": 0.0,
              "ModifierPolicy": "Refresh",
              "MaxStack": 1
            }
          ]
        }
      ],
      "Targeting": {
        "IndicatorDecal": "",
        "MaxRange": 700.0,
        "Radius": 0.0,
        "Width": 0.0
      },
      "Control": {
        "KnockbackStrength": 0.0,
        "PullStrength": 0.0
      },
      "Awaken": {
        "MaxGauge": 100.0,
        "GainOnBasicHit": 1.0,
        "GainOnWeaponSkillHit": 5.0,
        "DurationSec": 15.0,
        "AuraRadius": 0.0
      },
      "Trigger": { "TriggerSkillTag": "Arcanum.Skills.SkillName.None" }
    },
    "SkillClass": ""
  },
  {
    "Name": "BasicAttack_Bow",
    "SkillData": {
      "SkillNameTag": "Arcanum.Skills.BasicAttack.Bow",
      "DisplayName": "활 기본 공격",
      "SkillTypeTag": "Arcanum.Skills.SkillTypes.Active",
      "TargetTypeTag": "Arcanum.Skills.TargetingType.Unit",
      "TargetFilterTag": "Arcanum.Skills.TargetFilter.Enemy",
      "SkillVFXTag": [ "Arcanum.Skills.SkillVFX.None" ],
      "Icon": "",
      "CurrLevel": 0,
      "LevelModifiers": [
        {
          "Level": 0,
          "CastTime": 0.4,
          "OtherCharacterModifiers": [
            {
              "ModifierId": {
                "A": 0,
                "B": 0,
                "C": 0,
                "D": 0
              },
              "SourceTag": "Arcanum.Skills.BasicAttack.Bow",
              "StatTag": "Arcanum.BattleStat.Character.Regen.Health.Value",
              "ApplyTargetFilterTag": "Arcanum.Skills.TargetFilter.Enemy",
              "Value": {
                "Flat": -10.0,
                "Mul": 0.0
              },
              "bIsPermanent": false,
              "bAllowRefresh": true,
              "Duration": 0.0,
              "ModifierPolicy": "Refresh",
              "MaxStack": 1
            }
          ]
        },
        {
          "Level": 1,
          "CastTime": 0.4,
          "OtherCharacterModifiers": [
            {
              "ModifierId": {
                "A": 0,
                "B": 0,
                "C": 0,
                "D": 0
              },
              "SourceTag": "Arcanum.Skills.BasicAttack.Bow",
              "StatTag": "Arcanum.BattleStat.Character.Regen.Health.Value",
              "Value": {
                "Flat": -14.0,
                "Mul": 0.0
              },
              "bIsPermanent": false,
              "bAllowRefresh": true,
              "Duration": 0.0,
              "ModifierPolicy": "Refresh",
              "MaxStack": 1
            }
          ]
        },
        {
          "Level": 2,
          "CastTime": 0.4,
          "OtherCharacterModifiers": [
            {
              "ModifierId": {
                "A": 0,
                "B": 0,
                "C": 0,
                "D": 0
              },
              "SourceTag": "Arcanum.Skills.BasicAttack.Bow",
              "StatTag": "Arcanum.BattleStat.Character.Regen.Health.Value",
              "Value": {
                "Flat": -19.0,
                "Mul": 0.0
              },
              "bIsPermanent": false,
              "bAllowRefresh": true,
              "Duration": 0.0,
              "ModifierPolicy": "Refresh",
              "MaxStack": 1
            }
          ]
        },
        {
          "Level": 3,
          "CastTime": 0.4,
          "OtherCharacterModifiers": [
            {
              "ModifierId": {
                "A": 0,
                "B": 0,
                "C": 0,
                "D": 0
              },
              "SourceTag": "Arcanum.Skills.BasicAttack.Bow",
              "StatTag": "Arcanum.BattleStat.Character.Regen.Health.Value",
              "Value": {
                "Flat": -25.0,
                "Mul": 0.0
              },
              "bIsPermanent": false,
              "bAllowRefresh": true,
              "Duration": 0.0,
              "ModifierPolicy": "Refresh",
              "MaxStack": 1
            }
          ]
        },
        {
          "Level": 4,
          "CastTime": 0.4,
          "OtherCharacterModifiers": [
            {
              "ModifierId": {
                "A": 0,
                "B": 0,
                "C": 0,
                "D": 0
              },
              "SourceTag": "Arcanum.Skills.BasicAttack.Bow",
              "StatTag": "Arcanum.BattleStat.Character.Regen.Health.Value",
              "Value": {
                "Flat": -32.0,
                "Mul": 0.0
              },
              "bIsPermanent": false,
              "bAllowRefresh": true,
              "Duration": 0.0,
              "ModifierPolicy": "Refresh",
              "MaxStack": 1
            }
          ]
        },
        {
          "Level": 5,
          "CastTime": 0.4,
          "OtherCharacterModifiers": [
            {
              "ModifierId": {
                "A": 0,
                "B": 0,
                "C": 0,
                "D": 0
              },
              "SourceTag": "Arcanum.Skills.BasicAttack.Bow",
              "StatTag": "Arcanum.BattleStat.Character.Regen.Health.Value",
              "Value": {
                "Flat": -40.0,
                "Mul": 0.0
              },
              "bIsPermanent": false,
              "bAllowRefresh": true,
              "Duration": 0.0,
              "ModifierPolicy": "Refresh",
              "MaxStack": 1
            }
          ]
        }
      ],
      "Targeting": {
        "IndicatorDecal": "",
        "MaxRange": 800.0,
        "Radius": 0.0,
        "Width": 0.0
      },
      "Control": {
        "KnockbackStrength": 0.0,
        "PullStrength": 0.0
      },
      "Awaken": {
        "MaxGauge": 100.0,
        "GainOnBasicHit": 1.0,
        "GainOnWeaponSkillHit": 5.0,
        "DurationSec": 15.0,
        "AuraRadius": 0.0
      },
      "Trigger": { "TriggerSkillTag": "Arcanum.Skills.SkillName.None" }
    },
    "SkillClass": ""
  },
  {
    "Name": "BasicAttack_Shield",
    "SkillData": {
      "SkillNameTag": "Arcanum.Skills.BasicAttack.Shield",
      "DisplayName": "방패 기본 공격",
      "SkillTypeTag": "Arcanum.Skills.SkillTypes.Active",
      "TargetTypeTag": "Arcanum.Skills.TargetingType.Unit",
      "TargetFilterTag": "Arcanum.Skills.TargetFilter.Enemy",
      "SkillVFXTag": [ "Arcanum.Skills.SkillVFX.None" ],
      "Icon": "",
      "CurrLevel": 0,
      "LevelModifiers": [
        {
          "Level": 0,
          "CastTime": 0.4,
          "OtherCharacterModifiers": [
            {
              "ModifierId": {
                "A": 0,
                "B": 0,
                "C": 0,
                "D": 0
              },
              "SourceTag": "Arcanum.Skills.BasicAttack.Shield",
              "StatTag": "Arcanum.BattleStat.Character.Regen.Health.Value",
              "ApplyTargetFilterTag": "Arcanum.Skills.TargetFilter.Enemy",
              "Value": {
                "Flat": -10.0,
                "Mul": 0.0
              },
              "bIsPermanent": false,
              "bAllowRefresh": true,
              "Duration": 0.0,
              "ModifierPolicy": "Refresh",
              "MaxStack": 1
            }
          ]
        },
        {
          "Level": 1,
          "CastTime": 0.4,
          "OtherCharacterModifiers": [
            {
              "ModifierId": {
                "A": 0,
                "B": 0,
                "C": 0,
                "D": 0
              },
              "SourceTag": "Arcanum.Skills.BasicAttack.Shield",
              "StatTag": "Arcanum.BattleStat.Character.Regen.Health.Value",
              "Value": {
                "Flat": -14.0,
                "Mul": 0.0
              },
              "bIsPermanent": false,
              "bAllowRefresh": true,
              "Duration": 0.0,
              "ModifierPolicy": "Refresh",
              "MaxStack": 1
            }
          ]
        },
        {
          "Level": 2,
          "CastTime": 0.4,
          "OtherCharacterModifiers": [
            {
              "ModifierId": {
                "A": 0,
                "B": 0,
                "C": 0,
                "D": 0
              },
              "SourceTag": "Arcanum.Skills.BasicAttack.Shield",
              "StatTag": "Arcanum.BattleStat.Character.Regen.Health.Value",
              "Value": {
                "Flat": -19.0,
                "Mul": 0.0
              },
              "bIsPermanent": false,
              "bAllowRefresh": true,
              "Duration": 0.0,
              "ModifierPolicy": "Refresh",
              "MaxStack": 1
            }
          ]
        },
        {
          "Level": 3,
          "CastTime": 0.4,
          "OtherCharacterModifiers": [
            {
              "ModifierId": {
                "A": 0,
                "B": 0,
                "C": 0,
                "D": 0
              },
              "SourceTag": "Arcanum.Skills.BasicAttack.Shield",
              "StatTag": "Arcanum.BattleStat.Character.Regen.Health.Value",
              "Value": {
                "Flat": -25.0,
                "Mul": 0.0
              },
              "bIsPermanent": false,
              "bAllowRefresh": true,
              "Duration": 0.0,
              "ModifierPolicy": "Refresh",
              "MaxStack": 1
            }
          ]
        },
        {
          "Level": 4,
          "CastTime": 0.4,
          "OtherCharacterModifiers": [
            {
              "ModifierId": {
                "A": 0,
                "B": 0,
                "C": 0,
                "D": 0
              },
              "SourceTag": "Arcanum.Skills.BasicAttack.Shield",
              "StatTag": "Arcanum.BattleStat.Character.Regen.Health.Value",
              "Value": {
                "Flat": -32.0,
                "Mul": 0.0
              },
              "bIsPermanent": false,
              "bAllowRefresh": true,
              "Duration": 0.0,
              "ModifierPolicy": "Refresh",
              "MaxStack": 1
            }
          ]
        },
        {
          "Level": 5,
          "CastTime": 0.4,
          "OtherCharacterModifiers": [
            {
              "ModifierId": {
                "A": 0,
                "B": 0,
                "C": 0,
                "D": 0
              },
              "SourceTag": "Arcanum.Skills.BasicAttack.Shield",
              "StatTag": "Arcanum.BattleStat.Character.Regen.Health.Value",
              "Value": {
                "Flat": -40.0,
                "Mul": 0.0
              },
              "bIsPermanent": false,
              "bAllowRefresh": true,
              "Duration": 0.0,
              "ModifierPolicy": "Refresh",
              "MaxStack": 1
            }
          ]
        }
      ],
      "Targeting": {
        "IndicatorDecal": "",
        "MaxRange": 180.0,
        "Radius": 0.0,
        "Width": 0.0
      },
      "Control": {
        "KnockbackStrength": 0.0,
        "PullStrength": 0.0
      },
      "Awaken": {
        "MaxGauge": 100.0,
        "GainOnBasicHit": 1.0,
        "GainOnWeaponSkillHit": 5.0,
        "DurationSec": 15.0,
        "AuraRadius": 0.0
      },
      "Trigger": { "TriggerSkillTag": "Arcanum.Skills.SkillName.None" }
    },
    "SkillClass": ""
  },







  {
    "Name": "Trigger_BloodBurst",
    "SkillData": {
      "SkillNameTag": "Arcanum.Skills.Trigger.BloodBurst",
      "DisplayName": "혈폭",
      "SkillTypeTag": "Arcanum.Skills.SkillTypes.Active",
      "TargetTypeTag": "Arcanum.Skills.TargetingType.Unit",
      "TargetFilterTag": "Arcanum.Skills.TargetFilter.Enemy",
      "SkillVFXTag": [
        "Arcanum.Skills.SkillVFX.None"
      ],
      "Icon": "",
      "CurrLevel": 0,
      "LevelModifiers": [
        {
          "Level": 0,
          "CastTime": 0.0,
          "Cooldown": 0.0,
          "Cost": [],
          "Effect": "",
          "OtherCharacterModifiers": [
            {
              "ModifierId": {
                "A": 0,
                "B": 0,
                "C": 0,
                "D": 0
              },
              "SourceTag": "Arcanum.Skills.Trigger.BloodBurst",
              "StatTag": "Arcanum.BattleStat.Character.Regen.Health.Value",
              "ApplyTargetFilterTag": "Arcanum.Skills.TargetFilter.Enemy",
              "Value": {
                "Flat": -30.0,
                "Mul": 1.0
              },
              "bIsPermanent": false,
              "bAllowRefresh": true,
              "Duration": 0.0,
              "ModifierPolicy": "Refresh",
              "MaxStack": 1
            }
          ],
          "TargetEffect": ""
        },
        {
          "Level": 1,
          "CastTime": 0.0,
          "Cooldown": 0.0,
          "Cost": [],
          "Effect": "",
          "OtherCharacterModifiers": [
            {
              "ModifierId": {
                "A": 0,
                "B": 0,
                "C": 0,
                "D": 0
              },
              "SourceTag": "Arcanum.Skills.Trigger.BloodBurst",
              "StatTag": "Arcanum.BattleStat.Character.Regen.Health.Value",
              "ApplyTargetFilterTag": "Arcanum.Skills.TargetFilter.Enemy",
              "Value": {
                "Flat": -42.0,
                "Mul": 1.0
              },
              "bIsPermanent": false,
              "bAllowRefresh": true,
              "Duration": 0.0,
              "ModifierPolicy": "Refresh",
              "MaxStack": 1
            }
          ],
          "TargetEffect": ""
        },
        {
          "Level": 2,
          "CastTime": 0.0,
          "Cooldown": 0.0,
          "Cost": [],
          "Effect": "",
          "OtherCharacterModifiers": [
            {
              "ModifierId": {
                "A": 0,
                "B": 0,
                "C": 0,
                "D": 0
              },
              "SourceTag": "Arcanum.Skills.Trigger.BloodBurst",
              "StatTag": "Arcanum.BattleStat.Character.Regen.Health.Value",
              "ApplyTargetFilterTag": "Arcanum.Skills.TargetFilter.Enemy",
              "Value": {
                "Flat": -56.0,
                "Mul": 1.0
              },
              "bIsPermanent": false,
              "bAllowRefresh": true,
              "Duration": 0.0,
              "ModifierPolicy": "Refresh",
              "MaxStack": 1
            }
          ],
          "TargetEffect": ""
        },
        {
          "Level": 3,
          "CastTime": 0.0,
          "Cooldown": 0.0,
          "Cost": [],
          "Effect": "",
          "OtherCharacterModifiers": [
            {
              "ModifierId": {
                "A": 0,
                "B": 0,
                "C": 0,
                "D": 0
              },
              "SourceTag": "Arcanum.Skills.Trigger.BloodBurst",
              "StatTag": "Arcanum.BattleStat.Character.Regen.Health.Value",
              "ApplyTargetFilterTag": "Arcanum.Skills.TargetFilter.Enemy",
              "Value": {
                "Flat": -72.0,
                "Mul": 1.0
              },
              "bIsPermanent": false,
              "bAllowRefresh": true,
              "Duration": 0.0,
              "ModifierPolicy": "Refresh",
              "MaxStack": 1
            }
          ],
          "TargetEffect": ""
        },
        {
          "Level": 4,
          "CastTime": 0.0,
          "Cooldown": 0.0,
          "Cost": [],
          "Effect": "",
          "OtherCharacterModifiers": [
            {
              "ModifierId": {
                "A": 0,
                "B": 0,
                "C": 0,
                "D": 0
              },
              "SourceTag": "Arcanum.Skills.Trigger.BloodBurst",
              "StatTag": "Arcanum.BattleStat.Character.Regen.Health.Value",
              "ApplyTargetFilterTag": "Arcanum.Skills.TargetFilter.Enemy",
              "Value": {
                "Flat": -90.0,
                "Mul": 1.0
              },
              "bIsPermanent": false,
              "bAllowRefresh": true,
              "Duration": 0.0,
              "ModifierPolicy": "Refresh",
              "MaxStack": 1
            }
          ],
          "TargetEffect": ""
        },
        {
          "Level": 5,
          "CastTime": 0.0,
          "Cooldown": 0.0,
          "Cost": [],
          "Effect": "",
          "OtherCharacterModifiers": [
            {
              "ModifierId": {
                "A": 0,
                "B": 0,
                "C": 0,
                "D": 0
              },
              "SourceTag": "Arcanum.Skills.Trigger.BloodBurst",
              "StatTag": "Arcanum.BattleStat.Character.Regen.Health.Value",
              "ApplyTargetFilterTag": "Arcanum.Skills.TargetFilter.Enemy",
              "Value": {
                "Flat": -110.0,
                "Mul": 1.0
              },
              "bIsPermanent": false,
              "bAllowRefresh": true,
              "Duration": 0.0,
              "ModifierPolicy": "Refresh",
              "MaxStack": 1
            }
          ],
          "TargetEffect": ""
        }
      ],
      "Targeting": {
        "IndicatorDecal": "",
        "MaxRange": 0.0,
        "Radius": 250.0,
        "Width": 0.0
      },
      "Control": {
        "KnockbackStrength": 0.0,
        "PullStrength": 0.0
      },
      "Awaken": {
        "MaxGauge": 100.0,
        "GainOnBasicHit": 1.0,
        "GainOnWeaponSkillHit": 5.0,
        "DurationSec": 15.0,
        "AuraRadius": 0.0
      },
      "Trigger": {
        "TriggerSkillTag": "Arcanum.Skills.SkillName.None"
      }
    },
    "SkillClass": ""
  },

  {
    "Name": "Trigger_Execution",
    "SkillData": {
      "SkillNameTag": "Arcanum.Skills.Trigger.Execution",
      "DisplayName": "처단",
      "SkillTypeTag": "Arcanum.Skills.SkillTypes.Active",
      "TargetTypeTag": "Arcanum.Skills.TargetingType.Unit",
      "TargetFilterTag": "Arcanum.Skills.TargetFilter.Enemy",
      "SkillVFXTag": [
        "Arcanum.Skills.SkillVFX.None"
      ],
      "Icon": "",
      "CurrLevel": 0,
      "LevelModifiers": [
        {
          "Level": 0,
          "CastTime": 0.0,
          "Cooldown": 0.0,
          "Cost": [],
          "Effect": "",
          "OtherCharacterModifiers": [
            {
              "ModifierId": {
                "A": 0,
                "B": 0,
                "C": 0,
                "D": 0
              },
              "SourceTag": "Arcanum.Skills.Trigger.Execution",
              "StatTag": "Arcanum.BattleStat.Character.Regen.Health.Value",
              "ApplyTargetFilterTag": "Arcanum.Skills.TargetFilter.Enemy",
              "Value": {
                "Flat": -35.0,
                "Mul": 1.0
              },
              "bIsPermanent": false,
              "bAllowRefresh": true,
              "Duration": 0.0,
              "ModifierPolicy": "Refresh",
              "MaxStack": 1
            }
          ],
          "TargetEffect": ""
        },
        {
          "Level": 1,
          "CastTime": 0.0,
          "Cooldown": 0.0,
          "Cost": [],
          "Effect": "",
          "OtherCharacterModifiers": [
            {
              "ModifierId": {
                "A": 0,
                "B": 0,
                "C": 0,
                "D": 0
              },
              "SourceTag": "Arcanum.Skills.Trigger.Execution",
              "StatTag": "Arcanum.BattleStat.Character.Regen.Health.Value",
              "ApplyTargetFilterTag": "Arcanum.Skills.TargetFilter.Enemy",
              "Value": {
                "Flat": -49.0,
                "Mul": 1.0
              },
              "bIsPermanent": false,
              "bAllowRefresh": true,
              "Duration": 0.0,
              "ModifierPolicy": "Refresh",
              "MaxStack": 1
            }
          ],
          "TargetEffect": ""
        },
        {
          "Level": 2,
          "CastTime": 0.0,
          "Cooldown": 0.0,
          "Cost": [],
          "Effect": "",
          "OtherCharacterModifiers": [
            {
              "ModifierId": {
                "A": 0,
                "B": 0,
                "C": 0,
                "D": 0
              },
              "SourceTag": "Arcanum.Skills.Trigger.Execution",
              "StatTag": "Arcanum.BattleStat.Character.Regen.Health.Value",
              "ApplyTargetFilterTag": "Arcanum.Skills.TargetFilter.Enemy",
              "Value": {
                "Flat": -65.0,
                "Mul": 1.0
              },
              "bIsPermanent": false,
              "bAllowRefresh": true,
              "Duration": 0.0,
              "ModifierPolicy": "Refresh",
              "MaxStack": 1
            }
          ],
          "TargetEffect": ""
        },
        {
          "Level": 3,
          "CastTime": 0.0,
          "Cooldown": 0.0,
          "Cost": [],
          "Effect": "",
          "OtherCharacterModifiers": [
            {
              "ModifierId": {
                "A": 0,
                "B": 0,
                "C": 0,
                "D": 0
              },
              "SourceTag": "Arcanum.Skills.Trigger.Execution",
              "StatTag": "Arcanum.BattleStat.Character.Regen.Health.Value",
              "ApplyTargetFilterTag": "Arcanum.Skills.TargetFilter.Enemy",
              "Value": {
                "Flat": -83.0,
                "Mul": 1.0
              },
              "bIsPermanent": false,
              "bAllowRefresh": true,
              "Duration": 0.0,
              "ModifierPolicy": "Refresh",
              "MaxStack": 1
            }
          ],
          "TargetEffect": ""
        },
        {
          "Level": 4,
          "CastTime": 0.0,
          "Cooldown": 0.0,
          "Cost": [],
          "Effect": "",
          "OtherCharacterModifiers": [
            {
              "ModifierId": {
                "A": 0,
                "B": 0,
                "C": 0,
                "D": 0
              },
              "SourceTag": "Arcanum.Skills.Trigger.Execution",
              "StatTag": "Arcanum.BattleStat.Character.Regen.Health.Value",
              "ApplyTargetFilterTag": "Arcanum.Skills.TargetFilter.Enemy",
              "Value": {
                "Flat": -103.0,
                "Mul": 1.0
              },
              "bIsPermanent": false,
              "bAllowRefresh": true,
              "Duration": 0.0,
              "ModifierPolicy": "Refresh",
              "MaxStack": 1
            }
          ],
          "TargetEffect": ""
        },
        {
          "Level": 5,
          "CastTime": 0.0,
          "Cooldown": 0.0,
          "Cost": [],
          "Effect": "",
          "OtherCharacterModifiers": [
            {
              "ModifierId": {
                "A": 0,
                "B": 0,
                "C": 0,
                "D": 0
              },
              "SourceTag": "Arcanum.Skills.Trigger.Execution",
              "StatTag": "Arcanum.BattleStat.Character.Regen.Health.Value",
              "ApplyTargetFilterTag": "Arcanum.Skills.TargetFilter.Enemy",
              "Value": {
                "Flat": -125.0,
                "Mul": 1.0
              },
              "bIsPermanent": false,
              "bAllowRefresh": true,
              "Duration": 0.0,
              "ModifierPolicy": "Refresh",
              "MaxStack": 1
            }
          ],
          "TargetEffect": ""
        }
      ],
      "Targeting": {
        "IndicatorDecal": "",
        "MaxRange": 0.0,
        "Radius": 0.0,
        "Width": 0.0
      },
      "Control": {
        "KnockbackStrength": 0.0,
        "PullStrength": 0.0
      },
      "Awaken": {
        "MaxGauge": 100.0,
        "GainOnBasicHit": 1.0,
        "GainOnWeaponSkillHit": 5.0,
        "DurationSec": 15.0,
        "AuraRadius": 0.0
      },
      "Trigger": {
        "TriggerSkillTag": "Arcanum.Skills.SkillName.None"
      }
    },
    "SkillClass": ""
  },

  {
    "Name": "Trigger_Purification",
    "SkillData": {
      "SkillNameTag": "Arcanum.Skills.Trigger.Purification",
      "DisplayName": "정화",
      "SkillTypeTag": "Arcanum.Skills.SkillTypes.Active",
      "TargetTypeTag": "Arcanum.Skills.TargetingType.Unit",
      "TargetFilterTag": "Arcanum.Skills.TargetFilter.Enemy",
      "SkillVFXTag": [
        "Arcanum.Skills.SkillVFX.None"
      ],
      "Icon": "",
      "CurrLevel": 0,
      "LevelModifiers": [
        {
          "Level": 0,
          "CastTime": 0.0,
          "Cooldown": 0.0,
          "Cost": [],
          "Effect": "",
          "OtherCharacterModifiers": [
            {
              "ModifierId": {
                "A": 0,
                "B": 0,
                "C": 0,
                "D": 0
              },
              "SourceTag": "Arcanum.Skills.Trigger.Purification",
              "StatTag": "Arcanum.BattleStat.Character.Regen.Health.Value",
              "ApplyTargetFilterTag": "Arcanum.Skills.TargetFilter.Enemy",
              "Value": {
                "Flat": -32.0,
                "Mul": 1.0
              },
              "bIsPermanent": false,
              "bAllowRefresh": true,
              "Duration": 0.0,
              "ModifierPolicy": "Refresh",
              "MaxStack": 1
            }
          ],
          "TargetEffect": ""
        },
        {
          "Level": 1,
          "CastTime": 0.0,
          "Cooldown": 0.0,
          "Cost": [],
          "Effect": "",
          "OtherCharacterModifiers": [
            {
              "ModifierId": {
                "A": 0,
                "B": 0,
                "C": 0,
                "D": 0
              },
              "SourceTag": "Arcanum.Skills.Trigger.Purification",
              "StatTag": "Arcanum.BattleStat.Character.Regen.Health.Value",
              "ApplyTargetFilterTag": "Arcanum.Skills.TargetFilter.Enemy",
              "Value": {
                "Flat": -45.0,
                "Mul": 1.0
              },
              "bIsPermanent": false,
              "bAllowRefresh": true,
              "Duration": 0.0,
              "ModifierPolicy": "Refresh",
              "MaxStack": 1
            }
          ],
          "TargetEffect": ""
        },
        {
          "Level": 2,
          "CastTime": 0.0,
          "Cooldown": 0.0,
          "Cost": [],
          "Effect": "",
          "OtherCharacterModifiers": [
            {
              "ModifierId": {
                "A": 0,
                "B": 0,
                "C": 0,
                "D": 0
              },
              "SourceTag": "Arcanum.Skills.Trigger.Purification",
              "StatTag": "Arcanum.BattleStat.Character.Regen.Health.Value",
              "ApplyTargetFilterTag": "Arcanum.Skills.TargetFilter.Enemy",
              "Value": {
                "Flat": -60.0,
                "Mul": 1.0
              },
              "bIsPermanent": false,
              "bAllowRefresh": true,
              "Duration": 0.0,
              "ModifierPolicy": "Refresh",
              "MaxStack": 1
            }
          ],
          "TargetEffect": ""
        },
        {
          "Level": 3,
          "CastTime": 0.0,
          "Cooldown": 0.0,
          "Cost": [],
          "Effect": "",
          "OtherCharacterModifiers": [
            {
              "ModifierId": {
                "A": 0,
                "B": 0,
                "C": 0,
                "D": 0
              },
              "SourceTag": "Arcanum.Skills.Trigger.Purification",
              "StatTag": "Arcanum.BattleStat.Character.Regen.Health.Value",
              "ApplyTargetFilterTag": "Arcanum.Skills.TargetFilter.Enemy",
              "Value": {
                "Flat": -76.0,
                "Mul": 1.0
              },
              "bIsPermanent": false,
              "bAllowRefresh": true,
              "Duration": 0.0,
              "ModifierPolicy": "Refresh",
              "MaxStack": 1
            }
          ],
          "TargetEffect": ""
        },
        {
          "Level": 4,
          "CastTime": 0.0,
          "Cooldown": 0.0,
          "Cost": [],
          "Effect": "",
          "OtherCharacterModifiers": [
            {
              "ModifierId": {
                "A": 0,
                "B": 0,
                "C": 0,
                "D": 0
              },
              "SourceTag": "Arcanum.Skills.Trigger.Purification",
              "StatTag": "Arcanum.BattleStat.Character.Regen.Health.Value",
              "ApplyTargetFilterTag": "Arcanum.Skills.TargetFilter.Enemy",
              "Value": {
                "Flat": -94.0,
                "Mul": 1.0
              },
              "bIsPermanent": false,
              "bAllowRefresh": true,
              "Duration": 0.0,
              "ModifierPolicy": "Refresh",
              "MaxStack": 1
            }
          ],
          "TargetEffect": ""
        },
        {
          "Level": 5,
          "CastTime": 0.0,
          "Cooldown": 0.0,
          "Cost": [],
          "Effect": "",
          "OtherCharacterModifiers": [
            {
              "ModifierId": {
                "A": 0,
                "B": 0,
                "C": 0,
                "D": 0
              },
              "SourceTag": "Arcanum.Skills.Trigger.Purification",
              "StatTag": "Arcanum.BattleStat.Character.Regen.Health.Value",
              "ApplyTargetFilterTag": "Arcanum.Skills.TargetFilter.Enemy",
              "Value": {
                "Flat": -114.0,
                "Mul": 1.0
              },
              "bIsPermanent": false,
              "bAllowRefresh": true,
              "Duration": 0.0,
              "ModifierPolicy": "Refresh",
              "MaxStack": 1
            }
          ],
          "TargetEffect": ""
        }
      ],
      "Targeting": {
        "IndicatorDecal": "",
        "MaxRange": 0.0,
        "Radius": 0.0,
        "Width": 0.0
      },
      "Control": {
        "KnockbackStrength": 0.0,
        "PullStrength": 0.0
      },
      "Awaken": {
        "MaxGauge": 100.0,
        "GainOnBasicHit": 1.0,
        "GainOnWeaponSkillHit": 5.0,
        "DurationSec": 15.0,
        "AuraRadius": 0.0
      },
      "Trigger": {
        "TriggerSkillTag": "Arcanum.Skills.SkillName.None"
      }
    },
    "SkillClass": ""
  },






  {
    "Name": "Debuff_Bleed",
    "SkillData": {
      "SkillNameTag": "Arcanum.Skills.SkillVFX.Bleed",
      "DisplayName": "출혈",
      "SkillTypeTag": "Arcanum.Skills.SkillTypes.Passive",
      "TargetTypeTag": "Arcanum.Skills.TargetingType.Unit",
      "TargetFilterTag": "Arcanum.Skills.TargetFilter.Enemy",
      "SkillVFXTag": [
        "Arcanum.Skills.SkillVFX.Bleed"
      ],
      "Icon": "",
      "CurrLevel": 0,
      "LevelModifiers": [
        {
          "Level": 0,
          "CastTime": 0.0,
          "Cooldown": 0.0,
          "Cost": [],
          "Effect": "",
          "OtherCharacterModifiers": [
            {
              "ModifierId": {
                "A": 0,
                "B": 0,
                "C": 0,
                "D": 0
              },
              "SourceTag": "Arcanum.Skills.SkillVFX.Bleed",
              "StatTag": "Arcanum.BattleStat.Character.Regen.Health.Value",
              "ApplyTargetFilterTag": "Arcanum.Skills.TargetFilter.Enemy",
              "Value": {
                "Flat": -3.0,
                "Mul": 1.0
              },
              "bIsPermanent": false,
              "bAllowRefresh": true,
              "Duration": 5.0,
              "ModifierPolicy": "Stack",
              "MaxStack": 5
            }
          ],
          "TargetEffect": ""
        },
        {
          "Level": 1,
          "CastTime": 0.0,
          "Cooldown": 0.0,
          "Cost": [],
          "Effect": "",
          "OtherCharacterModifiers": [
            {
              "ModifierId": {
                "A": 0,
                "B": 0,
                "C": 0,
                "D": 0
              },
              "SourceTag": "Arcanum.Skills.SkillVFX.Bleed",
              "StatTag": "Arcanum.BattleStat.Character.Regen.Health.Value",
              "ApplyTargetFilterTag": "Arcanum.Skills.TargetFilter.Enemy",
              "Value": {
                "Flat": -4.0,
                "Mul": 1.0
              },
              "bIsPermanent": false,
              "bAllowRefresh": true,
              "Duration": 5.0,
              "ModifierPolicy": "Stack",
              "MaxStack": 5
            }
          ],
          "TargetEffect": ""
        },
        {
          "Level": 2,
          "CastTime": 0.0,
          "Cooldown": 0.0,
          "Cost": [],
          "Effect": "",
          "OtherCharacterModifiers": [
            {
              "ModifierId": {
                "A": 0,
                "B": 0,
                "C": 0,
                "D": 0
              },
              "SourceTag": "Arcanum.Skills.SkillVFX.Bleed",
              "StatTag": "Arcanum.BattleStat.Character.Regen.Health.Value",
              "ApplyTargetFilterTag": "Arcanum.Skills.TargetFilter.Enemy",
              "Value": {
                "Flat": -5.0,
                "Mul": 1.0
              },
              "bIsPermanent": false,
              "bAllowRefresh": true,
              "Duration": 5.0,
              "ModifierPolicy": "Stack",
              "MaxStack": 5
            }
          ],
          "TargetEffect": ""
        },
        {
          "Level": 3,
          "CastTime": 0.0,
          "Cooldown": 0.0,
          "Cost": [],
          "Effect": "",
          "OtherCharacterModifiers": [
            {
              "ModifierId": {
                "A": 0,
                "B": 0,
                "C": 0,
                "D": 0
              },
              "SourceTag": "Arcanum.Skills.SkillVFX.Bleed",
              "StatTag": "Arcanum.BattleStat.Character.Regen.Health.Value",
              "ApplyTargetFilterTag": "Arcanum.Skills.TargetFilter.Enemy",
              "Value": {
                "Flat": -6.0,
                "Mul": 1.0
              },
              "bIsPermanent": false,
              "bAllowRefresh": true,
              "Duration": 5.0,
              "ModifierPolicy": "Stack",
              "MaxStack": 5
            }
          ],
          "TargetEffect": ""
        },
        {
          "Level": 4,
          "CastTime": 0.0,
          "Cooldown": 0.0,
          "Cost": [],
          "Effect": "",
          "OtherCharacterModifiers": [
            {
              "ModifierId": {
                "A": 0,
                "B": 0,
                "C": 0,
                "D": 0
              },
              "SourceTag": "Arcanum.Skills.SkillVFX.Bleed",
              "StatTag": "Arcanum.BattleStat.Character.Regen.Health.Value",
              "ApplyTargetFilterTag": "Arcanum.Skills.TargetFilter.Enemy",
              "Value": {
                "Flat": -7.0,
                "Mul": 1.0
              },
              "bIsPermanent": false,
              "bAllowRefresh": true,
              "Duration": 5.0,
              "ModifierPolicy": "Stack",
              "MaxStack": 5
            }
          ],
          "TargetEffect": ""
        },
        {
          "Level": 5,
          "CastTime": 0.0,
          "Cooldown": 0.0,
          "Cost": [],
          "Effect": "",
          "OtherCharacterModifiers": [
            {
              "ModifierId": {
                "A": 0,
                "B": 0,
                "C": 0,
                "D": 0
              },
              "SourceTag": "Arcanum.Skills.SkillVFX.Bleed",
              "StatTag": "Arcanum.BattleStat.Character.Regen.Health.Value",
              "ApplyTargetFilterTag": "Arcanum.Skills.TargetFilter.Enemy",
              "Value": {
                "Flat": -8.0,
                "Mul": 1.0
              },
              "bIsPermanent": false,
              "bAllowRefresh": true,
              "Duration": 5.0,
              "ModifierPolicy": "Stack",
              "MaxStack": 5
            }
          ],
          "TargetEffect": ""
        }
      ],
      "Targeting": {
        "IndicatorDecal": "",
        "MaxRange": 0.0,
        "Radius": 0.0,
        "Width": 0.0
      },
      "Control": {
        "KnockbackStrength": 0.0,
        "PullStrength": 0.0
      },
      "Awaken": {
        "MaxGauge": 100.0,
        "GainOnBasicHit": 1.0,
        "GainOnWeaponSkillHit": 5.0,
        "DurationSec": 15.0,
        "AuraRadius": 0.0
      },
      "Trigger": {
        "TriggerSkillTag": "Arcanum.Skills.Trigger.BloodBurst"
      }
    },
    "SkillClass": ""
  },

  {
    "Name": "Debuff_Mark",
    "SkillData": {
      "SkillNameTag": "Arcanum.Skills.SkillVFX.Mark",
      "DisplayName": "표식",
      "SkillTypeTag": "Arcanum.Skills.SkillTypes.Passive",
      "TargetTypeTag": "Arcanum.Skills.TargetingType.Unit",
      "TargetFilterTag": "Arcanum.Skills.TargetFilter.Enemy",
      "SkillVFXTag": [
        "Arcanum.Skills.SkillVFX.Mark"
      ],
      "Icon": "",
      "CurrLevel": 0,
      "LevelModifiers": [
        {
          "Level": 0,
          "CastTime": 0.0,
          "Cooldown": 0.0,
          "Cost": [],
          "Effect": "",
          "OtherCharacterModifiers": [
            {
              "ModifierId": {
                "A": 0,
                "B": 0,
                "C": 0,
                "D": 0
              },
              "SourceTag": "Arcanum.Skills.SkillVFX.Mark",
              "StatTag": "Arcanum.BattleStat.Character.NonRegen.DamageReduction.Value",
              "ApplyTargetFilterTag": "Arcanum.Skills.TargetFilter.Enemy",
              "Value": {
                "Flat": -5.0,
                "Mul": 1.0
              },
              "bIsPermanent": false,
              "bAllowRefresh": true,
              "Duration": 5.0,
              "ModifierPolicy": "Stack",
              "MaxStack": 5
            }
          ],
          "TargetEffect": ""
        },
        {
          "Level": 1,
          "CastTime": 0.0,
          "Cooldown": 0.0,
          "Cost": [],
          "Effect": "",
          "OtherCharacterModifiers": [
            {
              "ModifierId": {
                "A": 0,
                "B": 0,
                "C": 0,
                "D": 0
              },
              "SourceTag": "Arcanum.Skills.SkillVFX.Mark",
              "StatTag": "Arcanum.BattleStat.Character.NonRegen.DamageReduction.Value",
              "ApplyTargetFilterTag": "Arcanum.Skills.TargetFilter.Enemy",
              "Value": {
                "Flat": -7.0,
                "Mul": 1.0
              },
              "bIsPermanent": false,
              "bAllowRefresh": true,
              "Duration": 5.0,
              "ModifierPolicy": "Stack",
              "MaxStack": 5
            }
          ],
          "TargetEffect": ""
        },
        {
          "Level": 2,
          "CastTime": 0.0,
          "Cooldown": 0.0,
          "Cost": [],
          "Effect": "",
          "OtherCharacterModifiers": [
            {
              "ModifierId": {
                "A": 0,
                "B": 0,
                "C": 0,
                "D": 0
              },
              "SourceTag": "Arcanum.Skills.SkillVFX.Mark",
              "StatTag": "Arcanum.BattleStat.Character.NonRegen.DamageReduction.Value",
              "ApplyTargetFilterTag": "Arcanum.Skills.TargetFilter.Enemy",
              "Value": {
                "Flat": -9.0,
                "Mul": 1.0
              },
              "bIsPermanent": false,
              "bAllowRefresh": true,
              "Duration": 5.0,
              "ModifierPolicy": "Stack",
              "MaxStack": 5
            }
          ],
          "TargetEffect": ""
        },
        {
          "Level": 3,
          "CastTime": 0.0,
          "Cooldown": 0.0,
          "Cost": [],
          "Effect": "",
          "OtherCharacterModifiers": [
            {
              "ModifierId": {
                "A": 0,
                "B": 0,
                "C": 0,
                "D": 0
              },
              "SourceTag": "Arcanum.Skills.SkillVFX.Mark",
              "StatTag": "Arcanum.BattleStat.Character.NonRegen.DamageReduction.Value",
              "ApplyTargetFilterTag": "Arcanum.Skills.TargetFilter.Enemy",
              "Value": {
                "Flat": -11.0,
                "Mul": 1.0
              },
              "bIsPermanent": false,
              "bAllowRefresh": true,
              "Duration": 5.0,
              "ModifierPolicy": "Stack",
              "MaxStack": 5
            }
          ],
          "TargetEffect": ""
        },
        {
          "Level": 4,
          "CastTime": 0.0,
          "Cooldown": 0.0,
          "Cost": [],
          "Effect": "",
          "OtherCharacterModifiers": [
            {
              "ModifierId": {
                "A": 0,
                "B": 0,
                "C": 0,
                "D": 0
              },
              "SourceTag": "Arcanum.Skills.SkillVFX.Mark",
              "StatTag": "Arcanum.BattleStat.Character.NonRegen.DamageReduction.Value",
              "ApplyTargetFilterTag": "Arcanum.Skills.TargetFilter.Enemy",
              "Value": {
                "Flat": -13.0,
                "Mul": 1.0
              },
              "bIsPermanent": false,
              "bAllowRefresh": true,
              "Duration": 5.0,
              "ModifierPolicy": "Stack",
              "MaxStack": 5
            }
          ],
          "TargetEffect": ""
        },
        {
          "Level": 5,
          "CastTime": 0.0,
          "Cooldown": 0.0,
          "Cost": [],
          "Effect": "",
          "OtherCharacterModifiers": [
            {
              "ModifierId": {
                "A": 0,
                "B": 0,
                "C": 0,
                "D": 0
              },
              "SourceTag": "Arcanum.Skills.SkillVFX.Mark",
              "StatTag": "Arcanum.BattleStat.Character.NonRegen.DamageReduction.Value",
              "ApplyTargetFilterTag": "Arcanum.Skills.TargetFilter.Enemy",
              "Value": {
                "Flat": -15.0,
                "Mul": 1.0
              },
              "bIsPermanent": false,
              "bAllowRefresh": true,
              "Duration": 5.0,
              "ModifierPolicy": "Stack",
              "MaxStack": 5
            }
          ],
          "TargetEffect": ""
        }
      ],
      "Targeting": {
        "IndicatorDecal": "",
        "MaxRange": 0.0,
        "Radius": 0.0,
        "Width": 0.0
      },
      "Control": {
        "KnockbackStrength": 0.0,
        "PullStrength": 0.0
      },
      "Awaken": {
        "MaxGauge": 100.0,
        "GainOnBasicHit": 1.0,
        "GainOnWeaponSkillHit": 5.0,
        "DurationSec": 15.0,
        "AuraRadius": 0.0
      },
      "Trigger": {
        "TriggerSkillTag": "Arcanum.Skills.Trigger.Execution"
      }
    },
    "SkillClass": ""
  },

  {
    "Name": "Debuff_Aegis",
    "SkillData": {
      "SkillNameTag": "Arcanum.Skills.SkillVFX.Aegis",
      "DisplayName": "수호",
      "SkillTypeTag": "Arcanum.Skills.SkillTypes.Passive",
      "TargetTypeTag": "Arcanum.Skills.TargetingType.Unit",
      "TargetFilterTag": "Arcanum.Skills.TargetFilter.Enemy",
      "SkillVFXTag": [
        "Arcanum.Skills.SkillVFX.Aegis"
      ],
      "Icon": "",
      "CurrLevel": 0,
      "LevelModifiers": [
        {
          "Level": 0,
          "CastTime": 0.0,
          "Cooldown": 0.0,
          "Cost": [],
          "Effect": "",
          "OtherCharacterModifiers": [
            {
              "ModifierId": {
                "A": 0,
                "B": 0,
                "C": 0,
                "D": 0
              },
              "SourceTag": "Arcanum.Skills.SkillVFX.Aegis",
              "StatTag": "Arcanum.BattleStat.Character.NonRegen.DamageReduction.Value",
              "ApplyTargetFilterTag": "Arcanum.Skills.TargetFilter.Enemy",
              "Value": {
                "Flat": -3.0,
                "Mul": 1.0
              },
              "bIsPermanent": false,
              "bAllowRefresh": true,
              "Duration": 5.0,
              "ModifierPolicy": "Stack",
              "MaxStack": 5
            }
          ],
          "TargetEffect": ""
        },
        {
          "Level": 1,
          "CastTime": 0.0,
          "Cooldown": 0.0,
          "Cost": [],
          "Effect": "",
          "OtherCharacterModifiers": [
            {
              "ModifierId": {
                "A": 0,
                "B": 0,
                "C": 0,
                "D": 0
              },
              "SourceTag": "Arcanum.Skills.SkillVFX.Aegis",
              "StatTag": "Arcanum.BattleStat.Character.NonRegen.DamageReduction.Value",
              "ApplyTargetFilterTag": "Arcanum.Skills.TargetFilter.Enemy",
              "Value": {
                "Flat": -4.0,
                "Mul": 1.0
              },
              "bIsPermanent": false,
              "bAllowRefresh": true,
              "Duration": 5.0,
              "ModifierPolicy": "Stack",
              "MaxStack": 5
            }
          ],
          "TargetEffect": ""
        },
        {
          "Level": 2,
          "CastTime": 0.0,
          "Cooldown": 0.0,
          "Cost": [],
          "Effect": "",
          "OtherCharacterModifiers": [
            {
              "ModifierId": {
                "A": 0,
                "B": 0,
                "C": 0,
                "D": 0
              },
              "SourceTag": "Arcanum.Skills.SkillVFX.Aegis",
              "StatTag": "Arcanum.BattleStat.Character.NonRegen.DamageReduction.Value",
              "ApplyTargetFilterTag": "Arcanum.Skills.TargetFilter.Enemy",
              "Value": {
                "Flat": -5.0,
                "Mul": 1.0
              },
              "bIsPermanent": false,
              "bAllowRefresh": true,
              "Duration": 5.0,
              "ModifierPolicy": "Stack",
              "MaxStack": 5
            }
          ],
          "TargetEffect": ""
        },
        {
          "Level": 3,
          "CastTime": 0.0,
          "Cooldown": 0.0,
          "Cost": [],
          "Effect": "",
          "OtherCharacterModifiers": [
            {
              "ModifierId": {
                "A": 0,
                "B": 0,
                "C": 0,
                "D": 0
              },
              "SourceTag": "Arcanum.Skills.SkillVFX.Aegis",
              "StatTag": "Arcanum.BattleStat.Character.NonRegen.DamageReduction.Value",
              "ApplyTargetFilterTag": "Arcanum.Skills.TargetFilter.Enemy",
              "Value": {
                "Flat": -6.0,
                "Mul": 1.0
              },
              "bIsPermanent": false,
              "bAllowRefresh": true,
              "Duration": 5.0,
              "ModifierPolicy": "Stack",
              "MaxStack": 5
            }
          ],
          "TargetEffect": ""
        },
        {
          "Level": 4,
          "CastTime": 0.0,
          "Cooldown": 0.0,
          "Cost": [],
          "Effect": "",
          "OtherCharacterModifiers": [
            {
              "ModifierId": {
                "A": 0,
                "B": 0,
                "C": 0,
                "D": 0
              },
              "SourceTag": "Arcanum.Skills.SkillVFX.Aegis",
              "StatTag": "Arcanum.BattleStat.Character.NonRegen.DamageReduction.Value",
              "ApplyTargetFilterTag": "Arcanum.Skills.TargetFilter.Enemy",
              "Value": {
                "Flat": -7.0,
                "Mul": 1.0
              },
              "bIsPermanent": false,
              "bAllowRefresh": true,
              "Duration": 5.0,
              "ModifierPolicy": "Stack",
              "MaxStack": 5
            }
          ],
          "TargetEffect": ""
        },
        {
          "Level": 5,
          "CastTime": 0.0,
          "Cooldown": 0.0,
          "Cost": [],
          "Effect": "",
          "OtherCharacterModifiers": [
            {
              "ModifierId": {
                "A": 0,
                "B": 0,
                "C": 0,
                "D": 0
              },
              "SourceTag": "Arcanum.Skills.SkillVFX.Aegis",
              "StatTag": "Arcanum.BattleStat.Character.NonRegen.DamageReduction.Value",
              "ApplyTargetFilterTag": "Arcanum.Skills.TargetFilter.Enemy",
              "Value": {
                "Flat": -8.0,
                "Mul": 1.0
              },
              "bIsPermanent": false,
              "bAllowRefresh": true,
              "Duration": 5.0,
              "ModifierPolicy": "Stack",
              "MaxStack": 5
            }
          ],
          "TargetEffect": ""
        }
      ],
      "Targeting": {
        "IndicatorDecal": "",
        "MaxRange": 0.0,
        "Radius": 0.0,
        "Width": 0.0
      },
      "Control": {
        "KnockbackStrength": 0.0,
        "PullStrength": 0.0
      },
      "Awaken": {
        "MaxGauge": 100.0,
        "GainOnBasicHit": 1.0,
        "GainOnWeaponSkillHit": 5.0,
        "DurationSec": 15.0,
        "AuraRadius": 0.0
      },
      "Trigger": {
        "TriggerSkillTag": "Arcanum.Skills.Trigger.Purification"
      }
    },
    "SkillClass": ""
  },














  {
    "Name": "Slash",
    "SkillData": {
      "SkillNameTag": "Arcanum.Skills.SkillName.Slash",
      "DisplayName": "슬래시",
      "SkillTypeTag": "Arcanum.Skills.SkillTypes.Active",
      "TargetTypeTag": "Arcanum.Skills.TargetingType.Direction",
      "TargetFilterTag": "Arcanum.Skills.TargetFilter.Enemy",
      "SkillVFXTag": [ "Arcanum.Skills.SkillVFX.Knockback" ],
      "Icon": "",
      "CurrLevel": 0,
      "LevelModifiers": [
        {
          "Level": 0,
          "CastTime": 0.0,
          "Cooldown": 0.0,
          "Cost": [],
          "Effect": "",
          "OtherCharacterModifiers": [
            {
              "ModifierId": {
                "A": 0,
                "B": 0,
                "C": 0,
                "D": 0
              },
              "SourceTag": "Arcanum.Skills.SkillName.Slash",
              "StatTag": "Arcanum.Skills.SkillVFX.Knockback",
              "ApplyTargetFilterTag": "Arcanum.Skills.TargetFilter.Enemy",
              "Value": {
                "Flat": 0.0,
                "Mul": 1.0
              },
              "bIsPermanent": false,
              "bAllowRefresh": false,
              "Duration": 3.0,
              "ModifierPolicy": "Refresh",
              "MaxStack": 1
            }
          ],
          "TargetEffect": ""
        }
      ]
    }
  },
  {
    "Name": "ChainBolt",
    "SkillData": {
      "SkillNameTag": "Arcanum.Skills.SkillName.ChainBolt",
      "DisplayName": "체인 볼트",
      "SkillTypeTag": "Arcanum.Skills.SkillTypes.Active",
      "TargetTypeTag": "Arcanum.Skills.TargetingType.Unit",
      "TargetFilterTag": "Arcanum.Skills.TargetFilter.Enemy",
      "SkillVFXTag": [ "Arcanum.Skills.SkillVFX.Shock" ],
      "Icon": "",
      "CurrLevel": 0,
      "LevelModifiers": [
        {
          "Level": 0,
          "CastTime": 0.0,
          "Cooldown": 0.0,
          "Cost": [],
          "Effect": "",
          "OtherCharacterModifiers": [
            {
              "ModifierId": {
                "A": 0,
                "B": 0,
                "C": 0,
                "D": 0
              },
              "SourceTag": "Arcanum.Skills.SkillName.ChainBolt",
              "StatTag": "Arcanum.Skills.SkillVFX.Shock",
              "ApplyTargetFilterTag": "Arcanum.Skills.TargetFilter.Enemy",
              "Value": {
                "Flat": 0.0,
                "Mul": 1.0
              },
              "bIsPermanent": false,
              "bAllowRefresh": true,
              "Duration": 5.0,
              "ModifierPolicy": "Refresh",
              "MaxStack": 5
            }
          ],
          "TargetEffect": ""
        }
      ]
    }
  },
  {
    "Name": "PiercingShot",
    "SkillData": {
      "SkillNameTag": "Arcanum.Skills.SkillName.PiercingShot",
      "DisplayName": "관통 사격",
      "SkillTypeTag": "Arcanum.Skills.SkillTypes.Active",
      "TargetTypeTag": "Arcanum.Skills.TargetingType.Direction",
      "TargetFilterTag": "Arcanum.Skills.TargetFilter.Enemy",
      "SkillVFXTag": [ "Arcanum.Skills.SkillVFX.MoveSpeed" ],
      "Icon": "",
      "CurrLevel": 0,
      "LevelModifiers": [
        {
          "Level": 0,
          "CastTime": 0.0,
          "Cooldown": 0.0,
          "Cost": [],
          "Effect": "",
          "OtherCharacterModifiers": [
            {
              "ModifierId": {
                "A": 0,
                "B": 0,
                "C": 0,
                "D": 0
              },
              "SourceTag": "Arcanum.Skills.SkillName.PiercingShot",
              "StatTag": "Arcanum.Skills.SkillVFX.MoveSpeed",
              "ApplyTargetFilterTag": "Arcanum.Skills.TargetFilter.Enemy",
              "Value": {
                "Flat": 0.0,
                "Mul": 1.0
              },
              "bIsPermanent": false,
              "bAllowRefresh": true,
              "Duration": 5.0,
              "ModifierPolicy": "Refresh",
              "MaxStack": 5
            }
          ],
          "TargetEffect": ""
        }
      ]
    }
  },
  {
    "Name": "ShockWave",
    "SkillData": {
      "SkillNameTag": "Arcanum.Skills.SkillName.ShockWave",
      "DisplayName": "충격파",
      "SkillTypeTag": "Arcanum.Skills.SkillTypes.Active",
      "TargetTypeTag": "Arcanum.Skills.TargetingType.Self",
      "TargetFilterTag": "Arcanum.Skills.TargetFilter.Enemy",
      "SkillVFXTag": [ "Arcanum.Skills.SkillVFX.Stun" ],
      "Icon": "",
      "CurrLevel": 0,
      "LevelModifiers": [
        {
          "Level": 0,
          "CastTime": 0.0,
          "Cooldown": 0.0,
          "Cost": [],
          "Effect": "",
          "OtherCharacterModifiers": [
            {
              "ModifierId": {
                "A": 0,
                "B": 0,
                "C": 0,
                "D": 0
              },
              "SourceTag": "Arcanum.Skills.SkillName.ShockWave",
              "StatTag": "Arcanum.Skills.SkillVFX.Stun",
              "ApplyTargetFilterTag": "Arcanum.Skills.TargetFilter.Enemy",
              "Value": {
                "Flat": 0.0,
                "Mul": 1.0
              },
              "bIsPermanent": false,
              "bAllowRefresh": false,
              "Duration": 3.0,
              "ModifierPolicy": "Refresh",
              "MaxStack": 1
            }
          ],
          "TargetEffect": ""
        }
      ]
    }
  },
  {
    "Name": "VoidEclipse",
    "SkillData": {
      "SkillNameTag": "Arcanum.Skills.SkillName.VoidEclipse",
      "DisplayName": "보이드 이클립스",
      "SkillTypeTag": "Arcanum.Skills.SkillTypes.Active",
      "TargetTypeTag": "Arcanum.Skills.TargetingType.Ground",
      "TargetFilterTag": "Arcanum.Skills.TargetFilter.Enemy",
      "SkillVFXTag": [ "Arcanum.Skills.SkillVFX.None" ],
      "Icon": "",
      "CurrLevel": 0,
      "LevelModifiers": [
        {
          "Level": 0,
          "CastTime": 0.0,
          "Cooldown": 0.0,
          "Cost": [],
          "Effect": "",
          "OtherCharacterModifiers": [],
          "TargetEffect": ""
        }
      ]
    }
  },
  {
    "Name": "SolarFlare",
    "SkillData": {
      "SkillNameTag": "Arcanum.Skills.SkillName.SolarFlare",
      "DisplayName": "솔라 플레어",
      "SkillTypeTag": "Arcanum.Skills.SkillTypes.Active",
      "TargetTypeTag": "Arcanum.Skills.TargetingType.Ground",
      "TargetFilterTag": "Arcanum.Skills.TargetFilter.Enemy",
      "SkillVFXTag": [ "Arcanum.Skills.SkillVFX.Burn" ],
      "Icon": "",
      "CurrLevel": 0,
      "LevelModifiers": [
        {
          "Level": 0,
          "CastTime": 0.0,
          "Cooldown": 0.0,
          "Cost": [],
          "Effect": "",
          "OtherCharacterModifiers": [
            {
              "ModifierId": {
                "A": 0,
                "B": 0,
                "C": 0,
                "D": 0
              },
              "SourceTag": "Arcanum.Skills.SkillName.SolarFlare",
              "StatTag": "Arcanum.Skills.SkillVFX.Burn",
              "ApplyTargetFilterTag": "Arcanum.Skills.TargetFilter.Enemy",
              "Value": {
                "Flat": 0.0,
                "Mul": 1.0
              },
              "bIsPermanent": false,
              "bAllowRefresh": true,
              "Duration": 5.0,
              "ModifierPolicy": "Refresh",
              "MaxStack": 5
            }
          ],
          "TargetEffect": ""
        }
      ]
    }
  }
]